extra_requirements/requirements-tests.txt
wfsim/__init__.py
wfsim/contexts.py
wfsim/load_resource.py
wfsim/pax_interface.py
wfsim/strax_interface.py
wfsim/units.py
wfsim/utils.py
wfsim/core/afterpulse.py
wfsim/core/pulse.py
wfsim/core/rawdata.py
wfsim/core/s1.py
wfsim/core/s2.py
wfsim/pax_datastructure/data_model.py
wfsim/pax_datastructure/datastructure.py
wfsim-1.2.2.dist-info/LICENSE
wfsim-1.2.2.dist-info/METADATA
wfsim-1.2.2.dist-info/WHEEL
wfsim-1.2.2.dist-info/top_level.txt
wfsim-1.2.2.dist-info/RECORD
