Metadata-Version: 2.1
Name: wfsim
Version: 1.2.2
Summary: XENONnT Waveform simulator
Home-page: https://github.com/XENONnT/wfsim
Author: Wfsim contributors, the XENON collaboration
License: UNKNOWN
Platform: UNKNOWN
Classifier: Development Status :: 5 - Production/Stable
Classifier: License :: OSI Approved :: BSD License
Classifier: Natural Language :: English
Classifier: Programming Language :: Python :: 3.9
Classifier: Programming Language :: Python :: 3.10
Classifier: Intended Audience :: Science/Research
Classifier: Programming Language :: Python :: Implementation :: CPython
Classifier: Topic :: Scientific/Engineering :: Physics
Requires-Python: >=3.9
License-File: LICENSE
Requires-Dist: strax >=1.6.0
Requires-Dist: utilix >=0.5.3
Requires-Dist: straxen >=2.2.0
Requires-Dist: uproot >=4.0.0
Requires-Dist: epix >=0.3.7
Requires-Dist: nestpy
Provides-Extra: docs
Requires-Dist: sphinx ; extra == 'docs'
Requires-Dist: sphinx-rtd-theme ; extra == 'docs'
Requires-Dist: nbsphinx ; extra == 'docs'
Requires-Dist: recommonmark ; extra == 'docs'
Requires-Dist: graphviz ; extra == 'docs'
